knlm_c.cp36-win_amd64.pyd
knlm/__init__.py
knlm/__main__.py
knlm-0.1.2.dist-info/LICENSE.txt
knlm-0.1.2.dist-info/METADATA
knlm-0.1.2.dist-info/WHEEL
knlm-0.1.2.dist-info/top_level.txt
knlm-0.1.2.dist-info/RECORD
